[
  {
    "id": "1",
    "name": "基础测绘",
    "nodeType": 1,
    "children": [
      {
        "id": "2",
        "name": "学校模型",
        "url": "http://mapgl.com/data/model/qx-xuexiao/tileset.json",
        "type": "3DTiles",
        "isShow": 0,
        "nodeType": 2
      },
      {
        "id": "12",
        "name": "杭州白膜",
        "url": "http://10.0.1.35/czm/jy/binjianglu/tileset.json",
        "type": "3DTiles",
        "isShow": 0,
        "nodeType": 2
      }
    ]
  },
  {
    "id": "4",
    "name": "国土空间规划",
    "url": "",
    "type": "",
    "nodeType": 1,
    "children": [
      {
        "id": "5",
        "name": "控制性详细规划",
        "url": "http://10.0.1.35/czm/jy/JYKG_DKGH/tileset.json",
        "type": "3DTiles",
        "nodeType": 2,
        "isShow": 0,
        "layerField": "GHDK",
        "layerHeight": 8
      },
      {
        "id": "6",
        "name": "道路红线",
        "url": "http://10.0.1.35/czm/jy/DLM/tileset.json",
        "type": "3DTiles",
        "layerField": "road",
        "isShow": 0,
        "nodeType": 2,
        "layerHeight": 8
      }
    ]
  }
]